mediator/__init__.py
mediator/common/__init__.py
mediator/common/factory/__init__.py
mediator/common/factory/base.py
mediator/common/factory/cascade.py
mediator/common/factory/factories.py
mediator/common/factory/mappers.py
mediator/common/factory/policies.py
mediator/common/factory/utils.py
mediator/common/handler/__init__.py
mediator/common/handler/base.py
mediator/common/handler/handlers.py
mediator/common/modifiers.py
mediator/common/registry/__init__.py
mediator/common/registry/base.py
mediator/common/registry/registry.py
mediator/common/registry/stores.py
mediator/common/types.py
mediator/event/__init__.py
mediator/event/aggregate.py
mediator/event/base.py
mediator/event/local.py
mediator/event/registry.py
mediator/request/__init__.py
mediator/request/base.py
mediator/request/local.py
mediator/request/registry.py
mediator/utils/__init__.py
mediator/utils/context.py
mediator/utils/inspection.py
python_mediator-0.7.0.dist-info/LICENSE
python_mediator-0.7.0.dist-info/WHEEL
python_mediator-0.7.0.dist-info/METADATA
python_mediator-0.7.0.dist-info/RECORD
