Metadata-Version: 2.1
Name: python-mediator
Version: 0.7.0
Summary: Python mediator bus microframework for CQRS + ES
Home-page: https://github.com/dlski/python-mediator
License: MIT
Keywords: mediator,cqrs,event-driven,enterprise
Author: Damian Łukawski
Author-email: damian@lukawscy.pl
Requires-Python: >=3.7,<3.11
Classifier: Development Status :: 4 - Beta
Classifier: Intended Audience :: Developers
Classifier: License :: OSI Approved :: MIT License
Classifier: Programming Language :: Python :: 3
Classifier: Programming Language :: Python :: 3 :: Only
Classifier: Programming Language :: Python :: 3.10
Classifier: Programming Language :: Python :: 3.7
Classifier: Programming Language :: Python :: 3.8
Classifier: Programming Language :: Python :: 3.9
Classifier: Programming Language :: Python :: Implementation :: CPython
Classifier: Programming Language :: Python :: Implementation :: PyPy
Classifier: Topic :: Software Development :: Libraries :: Python Modules
Project-URL: Repository, https://github.com/dlski/python-mediator
